elm/__init__.py
elm/elmk.cfg
elm/elmk.py
elm/elmr.cfg
elm/elmr.py
elm/mltools.py
elm-0.1.3.dist-info/AUTHORS.rst
elm-0.1.3.dist-info/LICENSE
elm-0.1.3.dist-info/METADATA
elm-0.1.3.dist-info/WHEEL
elm-0.1.3.dist-info/top_level.txt
elm-0.1.3.dist-info/RECORD
