Metadata-Version: 2.1
Name: elm
Version: 0.1.3
Summary: Python Extreme Learning Machine (ELM) is a machine learning technique used for classification/regression tasks.
Home-page: https://github.com/acba/elm
Author: Augusto Almeida
Author-email: augustocbenvenuto@gmail.com
License: BSD
Keywords: elm,machine learning,artificial intelligence,ai,regression,regressor,classifier,neural network,extreme learning machine
Platform: UNKNOWN
Classifier: Development Status :: 3 - Alpha
Classifier: Intended Audience :: Developers
Classifier: License :: OSI Approved :: BSD License
Classifier: Natural Language :: English
Classifier: Programming Language :: Python :: 2.7
Classifier: Programming Language :: Python :: 3
Classifier: Programming Language :: Python :: 3.4
Classifier: Topic :: Software Development
Classifier: Topic :: Software Development :: Libraries :: Python Modules
Classifier: Topic :: Scientific/Engineering
Classifier: Topic :: Scientific/Engineering :: Artificial Intelligence
Classifier: Topic :: Scientific/Engineering :: Mathematics
Requires-Dist: numpy (==1.15.4)
Requires-Dist: deap (==1.2.2)
Requires-Dist: optunity (==1.1.1)
Provides-Extra: testing
Requires-Dist: pytest; extra == 'testing'
